SoybeanNext/.gitignore
SoybeanNext/__init__.py
SoybeanNext/data/10_test_examples.vcf
SoybeanNext/data/model.yaml
SoybeanNext/data/n_trait.yaml
SoybeanNext/data/p_trait.yaml
SoybeanNext/data/train_example.csv
SoybeanNext/data/train_example.vcf
SoybeanNext/data/traits.yaml
SoybeanNext/data_process.py
SoybeanNext/eval.py
SoybeanNext/forward.py
SoybeanNext/reader.py
SoybeanNext/reader_cpu.py
SoybeanNext/remodel.py
SoybeanNext/SoyDNGP.py
SoybeanNext/train.py
SoybeanNext/utils.py
SoybeanNext/weight_map.py
soybeannext-0.1.0.0.dist-info/METADATA
soybeannext-0.1.0.0.dist-info/WHEEL
soybeannext-0.1.0.0.dist-info/RECORD
