Metadata-Version: 2.1
Name: soybeannext
Version: 0.1.0.0
Summary: A deeplearning driving bioinformatic toolkit
Author: XtLab
Requires-Python: >=3.10,<4.0
Classifier: Programming Language :: Python :: 3
Classifier: Programming Language :: Python :: 3.10
Classifier: Programming Language :: Python :: 3.11
